django_easycart-0.4.0.dist-info/DESCRIPTION.rst
django_easycart-0.4.0.dist-info/METADATA
django_easycart-0.4.0.dist-info/RECORD
django_easycart-0.4.0.dist-info/WHEEL
django_easycart-0.4.0.dist-info/metadata.json
django_easycart-0.4.0.dist-info/top_level.txt
easycart/__init__.py
easycart/cart.py
easycart/context_processors.py
easycart/urls.py
easycart/views.py
